dschemadiff.py
dschemadiff-0.2.0.dist-info/LICENSE
dschemadiff-0.2.0.dist-info/METADATA
dschemadiff-0.2.0.dist-info/WHEEL
dschemadiff-0.2.0.dist-info/top_level.txt
dschemadiff-0.2.0.dist-info/RECORD
