Metadata-Version: 2.1
Name: dschemadiff
Version: 0.2.0
Summary: A schema diff tool.
Author-email: Derek Anderson <public@kered.org>
Project-URL: Homepage, https://github.com/keredson/dschemadiff
Project-URL: Issues, https://github.com/keredson/dschemadiff/issues
Classifier: Programming Language :: Python :: 3
Classifier: License :: OSI Approved :: GNU General Public License v3 (GPLv3)
Classifier: Operating System :: OS Independent
Requires-Python: >=3.8
License-File: LICENSE
